{
    "version": "0.4",
    "title": "Team Member Block",
    "type": "section",
    "metadata": {
        "template_type": "section-team",
        "include_in_zip": "1",
        "elementor_pro_required": null,
        "wp_page_template": "elementor_header_footer"
    },
    "content": [
        {
            "id": "119c3ca7",
            "settings": {
                "structure": "30",
                "margin": {
                    "unit": "px",
                    "top": "0",
                    "right": 0,
                    "bottom": "0",
                    "left": 0,
                    "isLinked": false
                },
                "padding_mobile": {
                    "unit": "px",
                    "top": "20",
                    "right": "20",
                    "bottom": "20",
                    "left": "20",
                    "isLinked": true
                }
            },
            "elements": [
                {
                    "id": "1de32423",
                    "settings": {
                        "_column_size": 33,
                        "_inline_size": null
                    },
                    "elements": [
                        {
                            "id": "6d7824d9",
                            "settings": {
                                "ekit_team_image": {
                                    "url": "https:\/\/www.preemptive.hocud.com\/wp-content\/uploads\/portrait-of-handsome-man-with-beard.jpg",
                                    "id": 869
                                },
                                "ekit_team_name": "Kay Howarth",
                                "ekit_team_position": "Chairman",
                                "ekit_team_toggle_icon": "",
                                "ekit_team_show_short_description": "",
                                "ekit_team_short_description": "",
                                "ekit_team_social_icons": [
                                    {
                                        "icon": "icon icon-facebook",
                                        "label": "Facebook",
                                        "_id": "c393fd2",
                                        "ekit_team_label": "Facebook",
                                        "ekit_team_link": {
                                            "url": "#",
                                            "is_external": "",
                                            "nofollow": "",
                                            "custom_attributes": ""
                                        }
                                    },
                                    {
                                        "_id": "5f7a29b",
                                        "ekit_team_icons": {
                                            "value": "icon icon-twitter",
                                            "library": "ekiticons"
                                        },
                                        "ekit_team_label": "Twitter",
                                        "ekit_team_link": {
                                            "url": "#",
                                            "is_external": "",
                                            "nofollow": "",
                                            "custom_attributes": ""
                                        }
                                    },
                                    {
                                        "_id": "174720d",
                                        "ekit_team_icons": {
                                            "value": "fab fa-linkedin-in",
                                            "library": "fa-brands"
                                        },
                                        "ekit_team_label": "LinkedIn",
                                        "ekit_team_link": {
                                            "url": "#",
                                            "is_external": "",
                                            "nofollow": "",
                                            "custom_attributes": ""
                                        }
                                    }
                                ],
                                "ekit_team_description": "Donec ullamcorper nulla non metus auctor fringilla. Sed posuere consectetur est at lobortis. Nullam id dolor id nibh ultricies vehicula ut id elit. Maecenas faucibus mollis interdum. Cras justo odio, dapibus ac facilisis in, egestas eget quam. Cras mattis consectetur purus sit amet fermentum.",
                                "ekit_team_phone": "+11112233344",
                                "ekit_team_email": "info@example.com",
                                "ekit_team_content_border_radius": {
                                    "unit": "px",
                                    "top": "0",
                                    "right": "0",
                                    "bottom": "0",
                                    "left": "0",
                                    "isLinked": false
                                },
                                "ekit_team_name_color": "#020C1E",
                                "ekit_team_name_hover_color": "#033EA5",
                                "ekit_team_position_typography_typography": "custom",
                                "ekit_team_position_typography_font_size": {
                                    "unit": "px",
                                    "size": 14,
                                    "sizes": []
                                },
                                "ekit_team_position_typography_font_weight": "400",
                                "ekit_team_position_color": "#939EAB",
                                "ekit_team_modal_name_color": "#020C1E",
                                "ekit_team_modal_name_typography_typography": "custom",
                                "ekit_team_modal_name_typography_font_size": {
                                    "unit": "px",
                                    "size": 32,
                                    "sizes": []
                                },
                                "ekit_team_modal_name_typography_font_weight": "600",
                                "ekit_team_modal_name_typography_line_height": {
                                    "unit": "em",
                                    "size": 1.3,
                                    "sizes": []
                                },
                                "ekit_team_modal_position_color": "#939EAB",
                                "ekit_team_modal_position_typography_typography": "custom",
                                "ekit_team_modal_position_typography_font_size": {
                                    "unit": "px",
                                    "size": 15,
                                    "sizes": []
                                },
                                "ekit_team_info_color": "#44484D",
                                "ekit_team_info_hover_color": "#033EA5",
                                "ekit_team_icon_primary_color": "#939EAB",
                                "ekit_team_hover_primary_color": "#033EA5",
                                "__globals__": {
                                    "ekit_team_name_hover_color": "",
                                    "ekit_team_name_color": "",
                                    "ekit_team_position_color": "",
                                    "ekit_team_icon_primary_color": "",
                                    "ekit_team_hover_primary_color": "",
                                    "ekit_team_modal_name_color": "",
                                    "ekit_team_modal_position_color": "",
                                    "ekit_team_info_hover_color": "",
                                    "ekit_team_info_color": ""
                                },
                                "ekit_team_thumbnail_size": "medium"
                            },
                            "elements": [],
                            "isInner": false,
                            "widgetType": "elementskit-team",
                            "elType": "widget"
                        }
                    ],
                    "isInner": false,
                    "elType": "column"
                },
                {
                    "id": "777af351",
                    "settings": {
                        "_column_size": 33,
                        "_inline_size": null
                    },
                    "elements": [
                        {
                            "id": "43d0ea74",
                            "settings": {
                                "ekit_team_image": {
                                    "url": "https:\/\/www.preemptive.hocud.com\/wp-content\/uploads\/young-african-businessman-in-the-city-outdoors.jpg",
                                    "id": 870
                                },
                                "ekit_team_name": "Dawood Dixon",
                                "ekit_team_position": "Managing Director",
                                "ekit_team_toggle_icon": "",
                                "ekit_team_show_short_description": "",
                                "ekit_team_short_description": "",
                                "ekit_team_social_icons": [
                                    {
                                        "icon": "icon icon-facebook",
                                        "label": "Facebook",
                                        "_id": "c393fd2",
                                        "ekit_team_label": "Facebook",
                                        "ekit_team_link": {
                                            "url": "#",
                                            "is_external": "",
                                            "nofollow": "",
                                            "custom_attributes": ""
                                        }
                                    },
                                    {
                                        "_id": "5f7a29b",
                                        "ekit_team_icons": {
                                            "value": "icon icon-twitter",
                                            "library": "ekiticons"
                                        },
                                        "ekit_team_label": "Twitter",
                                        "ekit_team_link": {
                                            "url": "#",
                                            "is_external": "",
                                            "nofollow": "",
                                            "custom_attributes": ""
                                        }
                                    },
                                    {
                                        "_id": "174720d",
                                        "ekit_team_icons": {
                                            "value": "fab fa-linkedin-in",
                                            "library": "fa-brands"
                                        },
                                        "ekit_team_label": "LinkedIn",
                                        "ekit_team_link": {
                                            "url": "#",
                                            "is_external": "",
                                            "nofollow": "",
                                            "custom_attributes": ""
                                        }
                                    }
                                ],
                                "ekit_team_description": "Donec ullamcorper nulla non metus auctor fringilla. Sed posuere consectetur est at lobortis. Nullam id dolor id nibh ultricies vehicula ut id elit. Maecenas faucibus mollis interdum. Cras justo odio, dapibus ac facilisis in, egestas eget quam. Cras mattis consectetur purus sit amet fermentum.",
                                "ekit_team_phone": "+11112233344",
                                "ekit_team_email": "info@example.com",
                                "ekit_team_content_border_radius": {
                                    "unit": "px",
                                    "top": "0",
                                    "right": "0",
                                    "bottom": "0",
                                    "left": "0",
                                    "isLinked": false
                                },
                                "ekit_team_name_color": "#020C1E",
                                "ekit_team_name_hover_color": "#033EA5",
                                "ekit_team_position_typography_typography": "custom",
                                "ekit_team_position_typography_font_size": {
                                    "unit": "px",
                                    "size": 14,
                                    "sizes": []
                                },
                                "ekit_team_position_typography_font_weight": "400",
                                "ekit_team_position_color": "#939EAB",
                                "ekit_team_modal_name_color": "#020C1E",
                                "ekit_team_modal_name_typography_typography": "custom",
                                "ekit_team_modal_name_typography_font_size": {
                                    "unit": "px",
                                    "size": 32,
                                    "sizes": []
                                },
                                "ekit_team_modal_name_typography_font_weight": "600",
                                "ekit_team_modal_name_typography_line_height": {
                                    "unit": "em",
                                    "size": 1.3,
                                    "sizes": []
                                },
                                "ekit_team_modal_position_color": "#939EAB",
                                "ekit_team_modal_position_typography_typography": "custom",
                                "ekit_team_modal_position_typography_font_size": {
                                    "unit": "px",
                                    "size": 15,
                                    "sizes": []
                                },
                                "ekit_team_info_color": "#44484D",
                                "ekit_team_info_hover_color": "#033EA5",
                                "ekit_team_icon_primary_color": "#939EAB",
                                "ekit_team_hover_primary_color": "#033EA5",
                                "__globals__": {
                                    "ekit_team_name_hover_color": "",
                                    "ekit_team_name_color": "",
                                    "ekit_team_position_color": "",
                                    "ekit_team_icon_primary_color": "",
                                    "ekit_team_hover_primary_color": "",
                                    "ekit_team_modal_name_color": "",
                                    "ekit_team_modal_position_color": "",
                                    "ekit_team_info_hover_color": "",
                                    "ekit_team_info_color": ""
                                },
                                "ekit_team_thumbnail_size": "medium"
                            },
                            "elements": [],
                            "isInner": false,
                            "widgetType": "elementskit-team",
                            "elType": "widget"
                        }
                    ],
                    "isInner": false,
                    "elType": "column"
                },
                {
                    "id": "72982436",
                    "settings": {
                        "_column_size": 33,
                        "_inline_size": null
                    },
                    "elements": [
                        {
                            "id": "69534928",
                            "settings": {
                                "ekit_team_image": {
                                    "url": "https:\/\/www.preemptive.hocud.com\/wp-content\/uploads\/face-of-stressed-african-businessman-looking-sad-and-depressed-in-black-and-white.jpg",
                                    "id": 871
                                },
                                "ekit_team_name": "Stanley Fox",
                                "ekit_team_position": "Chief Executive",
                                "ekit_team_toggle_icon": "",
                                "ekit_team_show_short_description": "",
                                "ekit_team_short_description": "",
                                "ekit_team_social_icons": [
                                    {
                                        "icon": "icon icon-facebook",
                                        "label": "Facebook",
                                        "_id": "c393fd2",
                                        "ekit_team_label": "Facebook",
                                        "ekit_team_link": {
                                            "url": "#",
                                            "is_external": "",
                                            "nofollow": "",
                                            "custom_attributes": ""
                                        }
                                    },
                                    {
                                        "_id": "5f7a29b",
                                        "ekit_team_icons": {
                                            "value": "icon icon-twitter",
                                            "library": "ekiticons"
                                        },
                                        "ekit_team_label": "Twitter",
                                        "ekit_team_link": {
                                            "url": "#",
                                            "is_external": "",
                                            "nofollow": "",
                                            "custom_attributes": ""
                                        }
                                    },
                                    {
                                        "_id": "174720d",
                                        "ekit_team_icons": {
                                            "value": "fab fa-linkedin-in",
                                            "library": "fa-brands"
                                        },
                                        "ekit_team_label": "LinkedIn",
                                        "ekit_team_link": {
                                            "url": "#",
                                            "is_external": "",
                                            "nofollow": "",
                                            "custom_attributes": ""
                                        }
                                    }
                                ],
                                "ekit_team_description": "Donec ullamcorper nulla non metus auctor fringilla. Sed posuere consectetur est at lobortis. Nullam id dolor id nibh ultricies vehicula ut id elit. Maecenas faucibus mollis interdum. Cras justo odio, dapibus ac facilisis in, egestas eget quam. Cras mattis consectetur purus sit amet fermentum.",
                                "ekit_team_phone": "+11112233344",
                                "ekit_team_email": "info@example.com",
                                "ekit_team_content_border_radius": {
                                    "unit": "px",
                                    "top": "0",
                                    "right": "0",
                                    "bottom": "0",
                                    "left": "0",
                                    "isLinked": false
                                },
                                "ekit_team_name_color": "#020C1E",
                                "ekit_team_name_hover_color": "#033EA5",
                                "ekit_team_position_typography_typography": "custom",
                                "ekit_team_position_typography_font_size": {
                                    "unit": "px",
                                    "size": 14,
                                    "sizes": []
                                },
                                "ekit_team_position_typography_font_weight": "400",
                                "ekit_team_position_color": "#939EAB",
                                "ekit_team_modal_name_color": "#020C1E",
                                "ekit_team_modal_name_typography_typography": "custom",
                                "ekit_team_modal_name_typography_font_size": {
                                    "unit": "px",
                                    "size": 32,
                                    "sizes": []
                                },
                                "ekit_team_modal_name_typography_font_weight": "600",
                                "ekit_team_modal_name_typography_line_height": {
                                    "unit": "em",
                                    "size": 1.3,
                                    "sizes": []
                                },
                                "ekit_team_modal_position_color": "#939EAB",
                                "ekit_team_modal_position_typography_typography": "custom",
                                "ekit_team_modal_position_typography_font_size": {
                                    "unit": "px",
                                    "size": 15,
                                    "sizes": []
                                },
                                "ekit_team_info_color": "#44484D",
                                "ekit_team_info_hover_color": "#033EA5",
                                "ekit_team_icon_primary_color": "#939EAB",
                                "ekit_team_hover_primary_color": "#033EA5",
                                "__globals__": {
                                    "ekit_team_name_hover_color": "",
                                    "ekit_team_name_color": "",
                                    "ekit_team_position_color": "",
                                    "ekit_team_icon_primary_color": "",
                                    "ekit_team_hover_primary_color": "",
                                    "ekit_team_modal_name_color": "",
                                    "ekit_team_modal_position_color": "",
                                    "ekit_team_info_hover_color": "",
                                    "ekit_team_info_color": ""
                                },
                                "ekit_team_thumbnail_size": "medium"
                            },
                            "elements": [],
                            "isInner": false,
                            "widgetType": "elementskit-team",
                            "elType": "widget"
                        }
                    ],
                    "isInner": false,
                    "elType": "column"
                }
            ],
            "isInner": false,
            "elType": "section"
        }
    ],
    "page_settings": {
        "hide_title": "yes",
        "ha_grid_zindex": "1000",
        "background_background": "classic",
        "background_color": "#FBF5F1",
        "content_wrapper_html_tag": "section",
        "template": "elementor_header_footer"
    }
}